extenteten/__init__.py
extenteten/assertion.py
extenteten/attention.py
extenteten/batch.py
extenteten/classification.py
extenteten/classification_test.py
extenteten/collections.py
extenteten/control.py
extenteten/dynamic_length.py
extenteten/dynamic_length_test.py
extenteten/initializers.py
extenteten/invertible.py
extenteten/layer.py
extenteten/mask.py
extenteten/math.py
extenteten/mlp.py
extenteten/random.py
extenteten/regularization.py
extenteten/softmax.py
extenteten/summary.py
extenteten/train.py
extenteten/transform.py
extenteten/util.py
extenteten/variable.py
extenteten/variable_test.py
extenteten/cnn/__init__.py
extenteten/cnn/layer.py
extenteten/cnn/lenet.py
extenteten/cnn/lenet_test.py
extenteten/embedding/__init__.py
extenteten/embedding/bidirectional.py
extenteten/embedding/embeddings.py
extenteten/embedding/unidirectional.py
extenteten/rnn/__init__.py
extenteten/rnn/cell.py
extenteten/rnn/rnn.py
tensorflow_extenteten-0.0.22.dist-info/DESCRIPTION.rst
tensorflow_extenteten-0.0.22.dist-info/METADATA
tensorflow_extenteten-0.0.22.dist-info/RECORD
tensorflow_extenteten-0.0.22.dist-info/WHEEL
tensorflow_extenteten-0.0.22.dist-info/metadata.json
tensorflow_extenteten-0.0.22.dist-info/top_level.txt
