Metadata-Version: 2.0
Name: tensorflow-extenteten
Version: 0.0.22
Summary: TensorFlow extention library
Home-page: https://github.com/raviqqe/tensorflow-extenteten/
Author: Yota Toyama
Author-email: raviqqe@gmail.com
License: Public Domain
Platform: UNKNOWN
Classifier: Development Status :: 3 - Alpha
Classifier: Intended Audience :: Developers
Classifier: License :: Public Domain
Classifier: Programming Language :: Python :: 3.5
Classifier: Topic :: Scientific/Engineering :: Artificial Intelligence
Classifier: Topic :: System :: Networking
